MANIFEST.in
Readme.rst
arica.png
setup.py
clchoropleth/__init__.py
clchoropleth/add_comuna_code_to_svg.py
clchoropleth/choropleth.py
clchoropleth.egg-info/PKG-INFO
clchoropleth.egg-info/SOURCES.txt
clchoropleth.egg-info/dependency_links.txt
clchoropleth.egg-info/not-zip-safe
clchoropleth.egg-info/requires.txt
clchoropleth.egg-info/top_level.txt
clchoropleth/svgs/01.svg
clchoropleth/svgs/02.svg
clchoropleth/svgs/03.svg
clchoropleth/svgs/04.svg
clchoropleth/svgs/05.svg
clchoropleth/svgs/06.svg
clchoropleth/svgs/07.svg
clchoropleth/svgs/08.svg
clchoropleth/svgs/09.svg
clchoropleth/svgs/10.svg
clchoropleth/svgs/11.svg
clchoropleth/svgs/12.svg
clchoropleth/svgs/13.svg
clchoropleth/svgs/14.svg
clchoropleth/svgs/15.svg