Metadata-Version: 1.0
Name: clchoropleth
Version: 1.2
Summary: Creates SVG choropleths of Chilean regions
Home-page: http://github.com/slarrain/clchoropleth
Author: Santiago Larrain
Author-email: santiagolarrain@gmail.com
License: MIT
Platform: UNKNOWN
